example_scripts/__init__.py
example_scripts/development.py
example_scripts/plain_graph.py
example_scripts/run_citation_graph.py
example_scripts/run_example_cit.py
test/__init__.py
test/test_integration_Nyakatoke.py
test/test_integration_di_Nyakatoke1.py
test/test_integration_digraph.py
test/test_integration_graph.py
test/test_markov_walk_util.py
test/test_schaufe_type_3.py
test/test_schlaufen_construction.py
test/test_user_interface.py
test/test_util_and_helpfunctions.py
test/test_resources/__init__.py
test/test_resources/citation_example_graph.py
test/test_resources/graphs_two_restriction_sets.py
test/test_resources/input_more_restriction.py
test/test_resources/input_two_restriction.py
test/test_resources/plain_graph_integration.py
test/test_resources/nyakatoke_data/__init__.py
test/test_resources/nyakatoke_data/nyakatoke_network.py
test/test_util/__init__.py
test/test_util/json_citation_read_in.py
ugd/__init__.py
ugd/help_function/__init__.py
ugd/help_function/control_functions_digraph.py
ugd/help_function/control_functions_graph.py
ugd/help_function/graph_creation.py
ugd/help_function/util.py
ugd/help_function/util_statistic.py
ugd/high_level_interface/__init__.py
ugd/high_level_interface/construct_node_partition.py
ugd/high_level_interface/draw_simulations.py
ugd/high_level_interface/output_processing.py
ugd/high_level_interface/time_mixing_evaluation.py
ugd/high_level_interface/user_interface.py
ugd/high_level_interface/validation.py
ugd/locally_most_powerful_stat/__init__.py
ugd/locally_most_powerful_stat/lcl_mst_pwf_stat_statsmodels.py
ugd/locally_most_powerful_stat/util.py
ugd/markov_walk/__init__.py
ugd/markov_walk/constraint_violation_check.py
ugd/markov_walk/markov_walk.py
ugd/markov_walk/markov_walk_util.py
ugd/model/__init__.py
ugd/model/digraph.py
ugd/model/dinode.py
ugd/model/graph.py
ugd/model/node.py
ugd/schlaufen_construction/__init__.py
ugd/schlaufen_construction/di_schlaufen_construction.py
ugd-0.7.1.dist-info/LICENSE.txt
ugd-0.7.1.dist-info/METADATA
ugd-0.7.1.dist-info/WHEEL
ugd-0.7.1.dist-info/top_level.txt
ugd-0.7.1.dist-info/RECORD
