Metadata-Version: 2.1
Name: ugd
Version: 0.7.1
Summary: Drawing graphs uniformly at random subject to partition constraints (Partition Adjacency Matrix). Used for network testing.
Home-page: UNKNOWN
Author: Andrin Pelican
Author-email: pelicanandrin@gmail.com
License: UNKNOWN
Platform: UNKNOWN
Classifier: Programming Language :: Python :: 3
License-File: LICENSE.txt
Requires-Dist: numpy
Requires-Dist: matplotlib
Requires-Dist: statsmodels
Requires-Dist: pandas
